hexaeight_agent/__init__.py
hexaeight_agent/hexaeight_agent.py
hexaeight_agent/create/create-identity-for-child-agent.csx
hexaeight_agent/create/create-identity-for-parent-agent.csx
hexaeight_agent/demo/hexaeight_demo.py
hexaeight_agent/dlls/DeviceId.Linux.dll
hexaeight_agent/dlls/DeviceId.Linux.xml
hexaeight_agent/dlls/DeviceId.Mac.dll
hexaeight_agent/dlls/DeviceId.Mac.xml
hexaeight_agent/dlls/DeviceId.Windows.dll
hexaeight_agent/dlls/DeviceId.Windows.xml
hexaeight_agent/dlls/DeviceId.dll
hexaeight_agent/dlls/DeviceId.xml
hexaeight_agent/dlls/Hardware.Info.dll
hexaeight_agent/dlls/Hardware.Info.xml
hexaeight_agent/dlls/HexaEightASKClientLibrary.dll
hexaeight_agent/dlls/HexaEightAgent.dll
hexaeight_agent/dlls/HexaEightJWTLibrary.dll
hexaeight_agent/dlls/HexaEightMiddleware.dll
hexaeight_agent/dlls/Microsoft.IdentityModel.JsonWebTokens.dll
hexaeight_agent/dlls/Microsoft.IdentityModel.Logging.dll
hexaeight_agent/dlls/Microsoft.IdentityModel.Tokens.dll
hexaeight_agent/dlls/Newtonsoft.Json.dll
hexaeight_agent/dlls/Newtonsoft.Json.xml
hexaeight_agent/dlls/SQLite-net.dll
hexaeight_agent/dlls/SQLite.Interop.dll
hexaeight_agent/dlls/SQLitePCLRaw.core.dll
hexaeight_agent/dlls/System.Data.SQLite.dll
hexaeight_agent/dlls/System.IdentityModel.Tokens.Jwt.dll
hexaeight_agent/dlls/System.Security.Cryptography.Pkcs.dll
hexaeight_agent/dlls/System.Text.Json.dll
hexaeight_agent/dlls/System.Text.Json.xml
hexaeight_agent/dlls/SystemHelper.dll
hexaeight_agent/dlls/YamlDotNet.dll
hexaeight_agent/dlls/jose-jwt.dll
hexaeight_agent/dlls/linux-x64/SQLite.Interop.dll
hexaeight_agent/dlls/osx-x64/SQLite.Interop.dll
hexaeight_agent/dlls/win-x64/SQLite.Interop.dll
hexaeight_agent/dlls/win-x86/SQLite.Interop.dll
hexaeight_agent-1.6.807.dist-info/licenses/LICENSE
hexaeight_agent-1.6.807.dist-info/METADATA
hexaeight_agent-1.6.807.dist-info/WHEEL
hexaeight_agent-1.6.807.dist-info/top_level.txt
hexaeight_agent-1.6.807.dist-info/RECORD
