Metadata-Version: 2.4
Name: hexaeight-agent
Version: 1.6.807
Summary: HexaEight Agent - Python library for AI agent coordination, PubSub messaging, and task management
Author-email: HexaEight <support@hexaeight.com>
Maintainer-email: HexaEight <support@hexaeight.com>
License: Apache-2.0
Project-URL: Homepage, https://github.com/HexaEightTeam/hexaeight-agent
Project-URL: Documentation, https://github.com/HexaEightTeam/hexaeight-agent/blob/main/README.md
Project-URL: Repository, https://github.com/HexaEightTeam/hexaeight-agent.git
Project-URL: Bug Tracker, https://github.com/HexaEightTeam/hexaeight-agent/issues
Project-URL: Changelog, https://github.com/HexaEightTeam/hexaeight-agent/blob/main/CHANGELOG.md
Keywords: hexaeight,agent,pubsub,messaging,task-management,ai-coordination,multi-agent,identity,security
Classifier: Development Status :: 5 - Production/Stable
Classifier: Intended Audience :: Developers
Classifier: License :: OSI Approved :: Apache Software License
Classifier: Operating System :: OS Independent
Classifier: Programming Language :: Python :: 3
Classifier: Programming Language :: Python :: 3.8
Classifier: Programming Language :: Python :: 3.9
Classifier: Programming Language :: Python :: 3.10
Classifier: Programming Language :: Python :: 3.11
Classifier: Programming Language :: Python :: 3.12
Classifier: Topic :: Software Development :: Libraries :: Python Modules
Classifier: Topic :: System :: Distributed Computing
Classifier: Topic :: Communications
Classifier: Topic :: Security
Classifier: Topic :: Scientific/Engineering :: Artificial Intelligence
Requires-Python: >=3.8
License-File: LICENSE
Requires-Dist: pythonnet>=3.0.0
Provides-Extra: dev
Requires-Dist: pytest>=6.0; extra == "dev"
Requires-Dist: pytest-asyncio>=0.21.0; extra == "dev"
Requires-Dist: black>=22.0; extra == "dev"
Requires-Dist: flake8>=4.0; extra == "dev"
Requires-Dist: mypy>=0.991; extra == "dev"
Provides-Extra: examples
Requires-Dist: asyncio; extra == "examples"
Requires-Dist: aiofiles; extra == "examples"
Dynamic: license-file
